testapp_winstonyym/__init__.py
testapp_winstonyym/data/city_subzone_attr.json
testapp_winstonyym/testapp_winstonyym.py
testapp_winstonyym-0.1.0.dist-info/LICENSE
testapp_winstonyym-0.1.0.dist-info/WHEEL
testapp_winstonyym-0.1.0.dist-info/METADATA
testapp_winstonyym-0.1.0.dist-info/RECORD
