Metadata-Version: 2.1
Name: testapp-winstonyym
Version: 0.1.0
Summary: UAL Workshop demo
License: MIT
Author: winstonyym
Requires-Python: >=3.9,<4.0
Classifier: License :: OSI Approved :: MIT License
Classifier: Programming Language :: Python :: 3
Classifier: Programming Language :: Python :: 3.10
Classifier: Programming Language :: Python :: 3.9
Requires-Dist: matplotlib (>=3.7.1,<4.0.0)
Requires-Dist: pandas (>=2.0.0,<3.0.0)
